README.rst
lathermail_client.py
setup.py
lathermail_client.egg-info/PKG-INFO
lathermail_client.egg-info/SOURCES.txt
lathermail_client.egg-info/dependency_links.txt
lathermail_client.egg-info/requires.txt
lathermail_client.egg-info/top_level.txt